brusnika_data_validation/__init__.py
brusnika_data_validation/check_tests.py
brusnika_data_validation/Checking_the_dates.ipynb
brusnika_data_validation/credentials-pattern.json
brusnika_data_validation/db_queries.py
brusnika_data_validation/example_check_dates.ipynb
brusnika_data_validation/example_run_check_test.py
brusnika_data_validation/postprocessing.py
brusnika_data_validation/run_check_tests.py
brusnika_data_validation/utils/__init__.py
brusnika_data_validation/utils/calculation.py
brusnika_data_validation/utils/erp/__init__.py
brusnika_data_validation/utils/erp/authorization.py
brusnika_data_validation/utils/erp/bluebook.py
brusnika_data_validation/utils/erp/indicators.py
brusnika_data_validation/utils/erp/parameters.py
brusnika_data_validation/utils/erp/processes.py
brusnika_data_validation/utils/erp/versioning.py
brusnika_data_validation/utils/universal_data.py
brusnika_data_validation/validation/__init__.py
brusnika_data_validation/validation/object_passport/__init__.py
brusnika_data_validation/validation/object_passport/budget/__init__.py
brusnika_data_validation/validation/object_passport/budget/mapping.json
brusnika_data_validation/validation/object_passport/budget/test_co_bdr.py
brusnika_data_validation/validation/object_passport/budget/test_co_bdr_standarts.py
brusnika_data_validation/validation/object_passport/test_co_production.py
brusnika_data_validation/validation/object_passport/test_co_sales.py
brusnika_data_validation/validation/test_co_milestone_dates.py
brusnika_data_validation/validation/test_parcel_milestone_dates.py
brusnika_data_validation/validation/validator.py
brusnika_data_validation-0.1.5.dist-info/METADATA
brusnika_data_validation-0.1.5.dist-info/WHEEL
brusnika_data_validation-0.1.5.dist-info/RECORD
